MLLytics/__init__.py
MLLytics/interpretation.py
MLLytics/plots.py
MLLytics/regression.py
MLLytics/survival.py
MLLytics/test_example.py
MLLytics-0.2.2.dist-info/LICENSE
MLLytics-0.2.2.dist-info/METADATA
MLLytics-0.2.2.dist-info/WHEEL
MLLytics-0.2.2.dist-info/top_level.txt
MLLytics-0.2.2.dist-info/RECORD
